redis_management/__init__.py
redis_management/exceptions.py
redis_management/redis_manager.py
redis_management/settings.py
redis_management/test_redis_manager.py
redis_management-1.1.0.dist-info/LICENSE.txt
redis_management-1.1.0.dist-info/METADATA
redis_management-1.1.0.dist-info/WHEEL
redis_management-1.1.0.dist-info/top_level.txt
redis_management-1.1.0.dist-info/RECORD
