Metadata-Version: 2.1
Name: redis_management
Version: 1.1.0
Summary: A utility package for managing Redis keys.
Home-page: https://github.com/AAbbasRR/redis-manager.git
Author: Abbas Rahimzadeh
Author-email: arahimzadeh79@gmail.com
Classifier: Programming Language :: Python :: 3
Classifier: License :: OSI Approved :: MIT License
Classifier: Operating System :: OS Independent
License-File: LICENSE.txt
Requires-Dist: redis
Requires-Dist: python-decouple
Requires-Dist: cryptography ==42.0.8
